ecosizer_engine_package/__init__.py
ecosizer_engine_package/constants/Constants.py
ecosizer_engine_package/constants/__init__.py
ecosizer_engine_package/data/__init__.py
ecosizer_engine_package/data/load_shapes/__init__.py
ecosizer_engine_package/data/load_shapes/apartment.json
ecosizer_engine_package/data/load_shapes/elementary_school.json
ecosizer_engine_package/data/load_shapes/food_service_a.json
ecosizer_engine_package/data/load_shapes/food_service_b.json
ecosizer_engine_package/data/load_shapes/junior_high.json
ecosizer_engine_package/data/load_shapes/mens_dorm.json
ecosizer_engine_package/data/load_shapes/motel.json
ecosizer_engine_package/data/load_shapes/multi_family.json
ecosizer_engine_package/data/load_shapes/nursing_home.json
ecosizer_engine_package/data/load_shapes/office_building.json
ecosizer_engine_package/data/load_shapes/senior_high.json
ecosizer_engine_package/data/load_shapes/womens_dorm.json
ecosizer_engine_package/engine/BuildingCreator.py
ecosizer_engine_package/engine/EcosizerEngine.py
ecosizer_engine_package/engine/SystemCreator.py
ecosizer_engine_package/engine/__init__.py
ecosizer_engine_package/objects/Building.py
ecosizer_engine_package/objects/SystemConfig.py
ecosizer_engine_package/objects/__init__.py
ecosizer_engine_package/objects/systemConfigUtils.py
ecosizer_engine_package/objects/systems/ParallelLoopTank.py
ecosizer_engine_package/objects/systems/SwingTank.py
ecosizer_engine_package/objects/systems/__init__.py
ecosizer_engine-1.0.8.dist-info/METADATA
ecosizer_engine-1.0.8.dist-info/WHEEL
ecosizer_engine-1.0.8.dist-info/top_level.txt
ecosizer_engine-1.0.8.dist-info/RECORD
